README.md
docs/LiteLLM_Models.md
docs/emoji.md
docs/entrypoint_pr_gen_context.md
docs/entrypoint_pr_gen_summary.md
docs/entrypoint_pr_gen_title.md
docs/gh-actions-update.md
docs/logtools.md
docs/openai_tools.md
docs/push.md
klingon_tools/README.md
klingon_tools/__init__.py
klingon_tools/audit/code_audit.md
klingon_tools/audit/code_audit_template.j2
klingon_tools/entrypoints.py
klingon_tools/gh_actions_update.py
klingon_tools/git_commit_fix.py
klingon_tools/git_commit_validate.py
klingon_tools/git_log_helper.py
klingon_tools/git_push.py
klingon_tools/git_stage.py
klingon_tools/git_tools.py
klingon_tools/git_unstage.py
klingon_tools/git_user_info.py
klingon_tools/kstart.py
klingon_tools/ktest.py
klingon_tools/litellm_model_cache.py
klingon_tools/litellm_tools.py
klingon_tools/log_msg.py
klingon_tools/log_tools.py
klingon_tools/openai_tools.py
klingon_tools/pre_commit.py
klingon_tools/push.py
klingon_tools/utils.py
klingon_tools-2.1.6.dist-info/LICENSE.md
klingon_tools-2.1.6.dist-info/METADATA
klingon_tools-2.1.6.dist-info/WHEEL
klingon_tools-2.1.6.dist-info/entry_points.txt
klingon_tools-2.1.6.dist-info/RECORD
