Metadata-Version: 2.1
Name: klingon_tools
Version: 2.1.6
Summary: A set of utilities for running and logging shell commands in a user-friendly manner.
Home-page: https://github.com/djh00t/klingon_tools
License: MIT
Author: David Hooton
Author-email: klingon_tools+david@hooton.org
Requires-Python: >=3.9,<4.0
Classifier: License :: OSI Approved :: MIT License
Classifier: Programming Language :: Python :: 3
Classifier: Programming Language :: Python :: 3.9
Classifier: Programming Language :: Python :: 3.10
Classifier: Programming Language :: Python :: 3.11
Classifier: Programming Language :: Python :: 3.12
Classifier: Programming Language :: Python :: 3.13
Requires-Dist: emoji (>=2.14.0,<3.0.0)
Requires-Dist: gitpython (>=3.1.43,<4.0.0)
Requires-Dist: httpx (>=0.27.0,<0.28.0)
Requires-Dist: iniconfig (>=2.0.0,<3.0.0)
Requires-Dist: jinja2 (>=3.1.4,<4.0.0)
Requires-Dist: litellm (>=1.44.4,<2.0.0)
Requires-Dist: openai (>=1.42.0,<2.0.0)
Requires-Dist: packaging (>=24.1,<25.0)
Requires-Dist: pre-commit (>=3.8.0,<4.0.0)
Requires-Dist: psutil (>=6.0.0,<7.0.0)
Requires-Dist: pytest-depends (>=1.0.1,<2.0.0)
Requires-Dist: pytest-timeout (>=2.3.1,<3.0.0)
Requires-Dist: pyyaml (>=6.0.2,<7.0.0)
Requires-Dist: requests (>=2.32.3,<3.0.0)
Requires-Dist: ruamel-yaml (>=0.18.6,<0.19.0)
Requires-Dist: tabulate (>=0.9.0,<0.10.0)
Requires-Dist: toml (>=0.10.2,<0.11.0)
Requires-Dist: types-requests (>=2.32.0.20250306,<3.0.0.0)
Project-URL: Repository, https://github.com/djh00t/klingon_tools
